pyroxi/__init__.py
pyroxi/exceptions.py
pyroxi/core/__init__.py
pyroxi/core/connection.py
pyroxi/core/manager.py
pyroxi/packet/__init__.py
pyroxi/packet/builder.py
pyroxi/packet/parser.py
pyroxi-1.0.0.dist-info/METADATA
pyroxi-1.0.0.dist-info/WHEEL
pyroxi-1.0.0.dist-info/licenses/LICENSE
pyroxi-1.0.0.dist-info/RECORD
