Metadata-Version: 2.4
Name: pyroxi
Version: 1.0.0
Summary: High-performance Python proxy library with SOCKS5 and HTTP support, featuring multi-proxy load balancing, automatic failover, and binary networking protocols.
Project-URL: Homepage, https://github.com/bettercallninja/pyroxi
Project-URL: Repository, https://github.com/bettercallninja/pyroxi
Project-URL: Bug Reports, https://github.com/bettercallninja/pyroxi/issues
Project-URL: Source, https://github.com/bettercallninja/pyroxi
Author: bettercallninja
License: MIT
License-File: LICENSE
Keywords: async,binary-protocol,failover,high-performance,http-proxy,load-balancing,multi-proxy,networking,proxy,proxy-pool,proxy-server,socks5
Classifier: Development Status :: 5 - Production/Stable
Classifier: Framework :: AsyncIO
Classifier: Intended Audience :: Developers
Classifier: License :: OSI Approved :: MIT License
Classifier: Operating System :: OS Independent
Classifier: Programming Language :: Python :: 3
Classifier: Programming Language :: Python :: 3.7
Classifier: Programming Language :: Python :: 3.8
Classifier: Programming Language :: Python :: 3.9
Classifier: Programming Language :: Python :: 3.10
Classifier: Programming Language :: Python :: 3.11
Classifier: Programming Language :: Python :: 3.12
Classifier: Topic :: Internet :: Proxy Servers
Classifier: Topic :: Software Development :: Testing
Classifier: Topic :: System :: Networking
Requires-Python: >=3.7
